{"note":"This file is an internal implementation detail to speed up HTML report generation. Its format can change at any time. You might be looking for the JSON report: https://coverage.rtfd.io/cmd.html#cmd-json","format":5,"version":"7.6.8","globals":"c59896a8b81211df2f40f97ccd5d100b","files":{"z_5f5a17c013354698___init___py":{"hash":"3c77fc9ef7f887ac2508d4109cf92472","index":{"url":"z_5f5a17c013354698___init___py.html","file":"app/__init__.py","description":"","nums":{"precision":0,"n_files":1,"n_statements":0,"n_excluded":0,"n_missing":0,"n_branches":0,"n_partial_branches":0,"n_missing_branches":0}}},"z_5f5a17c013354698_calculator_py":{"hash":"1191272769fceda3e5b06a14dc813eb1","index":{"url":"z_5f5a17c013354698_calculator_py.html","file":"app/calculator.py","description":"","nums":{"precision":0,"n_files":1,"n_statements":10,"n_excluded":0,"n_missing":0,"n_branches":0,"n_partial_branches":0,"n_missing_branches":0}}},"z_a44f0ac069e85531___init___py":{"hash":"3c77fc9ef7f887ac2508d4109cf92472","index":{"url":"z_a44f0ac069e85531___init___py.html","file":"tests/__init__.py","description":"","nums":{"precision":0,"n_files":1,"n_statements":0,"n_excluded":0,"n_missing":0,"n_branches":0,"n_partial_branches":0,"n_missing_branches":0}}},"z_a44f0ac069e85531_test_calculator_py":{"hash":"1aa1aef04b6628a9494c5f17d8d4901f","index":{"url":"z_a44f0ac069e85531_test_calculator_py.html","file":"tests/test_calculator.py","description":"","nums":{"precision":0,"n_files":1,"n_statements":19,"n_excluded":0,"n_missing":0,"n_branches":0,"n_partial_branches":0,"n_missing_branches":0}}}}}